des/des_control_unit.v
module des_control_unit (
    input wire clk,             // Đồng hồ hệ thống
    input wire rst_n,           // Reset tích cực mức thấp
    input wire start,           // Tín hiệu bắt đầu xử lý
    input wire key_ready,       // Tín hiệu khóa đã sẵn sàng
    input wire data_ready,      // Tín hiệu dữ liệu đầu vào đã sẵn sàng
    output reg done,            // Tín hiệu hoàn thành xử lý
    output reg error,           // Tín hiệu báo lỗi
    output reg [4:0] round_count, // Bộ đếm vòng lặp (0-16)
    
    // Tín hiệu điều khiển các khối datapath
    output reg en_ip,           // Enable Initial Permutation
    output reg en_fp,           // Enable Final Permutation
    output reg en_expansion,    // Enable Expansion
    output reg en_key_mixing,   // Enable Key Mixing (XOR)
    output reg en_sbox,         // Enable S-Box
    output reg en_pbox,         // Enable P-Box
    output reg en_feistel,      // Enable Feistel Network
    output reg en_key_schedule, // Enable Key Schedule
    
    // Tín hiệu chọn dữ liệu
    output reg sel_input,       // 1: Chọn dữ liệu đầu vào, 0: Chọn dữ liệu vòng lặp
    output reg sel_output,      // 1: Xuất dữ liệu ra ngoài, 0: Giữ dữ liệu trong vòng lặp
    
    // Tín hiệu quản lý trạng thái
    output reg [1:0] state      // Trạng thái hiện tại (00: IDLE, 01: RUN, 10: DONE, 11: ERROR)
);

    // Định nghĩa các trạng thái
    localparam IDLE = 2'b00;
    localparam RUN  = 2'b01;
    localparam DONE = 2'b10;
    localparam ERROR = 2'b11;

    // Thanh ghi trạng thái
    reg [1:0] next_state;

    // Quản lý trạng thái - Sequential logic
    always @(posedge clk or negedge rst_n) begin
        if (!rst_n) begin
            state <= IDLE;
            round_count <= 5'd0;
        end else begin
            state <= next_state;
            
            // Quản lý bộ đếm vòng lặp
            if (state == IDLE) begin
                round_count <= 5'd0;
            end else if (state == RUN) begin
                if (round_count < 16)
                    round_count <= round_count + 1'b1;
            end
        end
    end

    // Xác định trạng thái tiếp theo - Combinational logic
    always @(*) begin
        // Giá trị mặc định
        next_state = state;
        
        case (state)
            IDLE: begin
                if (start && key_ready && data_ready)
                    next_state = RUN;
                else if (start && (!key_ready || !data_ready))
                    next_state = ERROR;
            end
            
            RUN: begin
                if (round_count == 16)
                    next_state = DONE;
            end
            
            DONE: begin
                next_state = IDLE; // Quay về trạng thái IDLE sau khi xử lý xong
            end
            
            ERROR: begin
                if (start && key_ready && data_ready)
                    next_state = IDLE; // Quay về IDLE khi các điều kiện đã sẵn sàng
            end
            
            default: next_state = IDLE;
        endcase
    end

    // Sinh tín hiệu điều khiển dựa vào trạng thái - Combinational logic
    always @(*) begin
        // Giá trị mặc định
        done = 1'b0;
        error = 1'b0;
        en_ip = 1'b0;
        en_fp = 1'b0;
        en_expansion = 1'b0;
        en_key_mixing = 1'b0;
        en_sbox = 1'b0;
        en_pbox = 1'b0;
        en_feistel = 1'b0;
        en_key_schedule = 1'b0;
        sel_input = 1'b0;
        sel_output = 1'b0;
        
        case (state)
            IDLE: begin
                sel_input = 1'b1;  // Chọn dữ liệu đầu vào
                en_ip = start && key_ready && data_ready; // Kích hoạt IP khi bắt đầu
                en_key_schedule = start && key_ready; // Kích hoạt key schedule khi bắt đầu
            end
            
            RUN: begin
                // Kích hoạt các khối datapath trong vòng lặp
                en_expansion = 1'b1;
                en_key_mixing = 1'b1;
                en_sbox = 1'b1;
                en_pbox = 1'b1;
                en_feistel = 1'b1;
                en_key_schedule = 1'b1; // Sinh khóa con cho vòng hiện tại
                
                // Vòng cuối cùng (16) thì chuẩn bị hoàn thành
                if (round_count == 16)
                    en_fp = 1'b1; // Kích hoạt Final Permutation
            end
            
            DONE: begin
                done = 1'b1;
                sel_output = 1'b1; // Cho phép xuất dữ liệu ra ngoài
            end
            
            ERROR: begin
                error = 1'b1;
            end
        endcase
    end

endmodule

des/des_control_unit_tb.v
`timescale 1ns/1ps

module des_control_unit_tb();

    // Định nghĩa các tín hiệu
    reg clk;
    reg rst_n;
    reg start;
    reg key_ready;
    reg data_ready;
    
    wire done;
    wire error;
    wire [4:0] round_count;
    wire en_ip, en_fp, en_expansion, en_key_mixing;
    wire en_sbox, en_pbox, en_feistel, en_key_schedule;
    wire sel_input, sel_output;
    wire [1:0] state;
    
    // Định nghĩa các trạng thái để theo dõi dễ dàng
    localparam IDLE = 2'b00;
    localparam RUN  = 2'b01;
    localparam DONE = 2'b10;
    localparam ERROR = 2'b11;
    
    // Instantiate DES Control Unit
    des_control_unit dut (
        .clk(clk),
        .rst_n(rst_n),
        .start(start),
        .key_ready(key_ready),
        .data_ready(data_ready),
        .done(done),
        .error(error),
        .round_count(round_count),
        .en_ip(en_ip),
        .en_fp(en_fp),
        .en_expansion(en_expansion),
        .en_key_mixing(en_key_mixing),
        .en_sbox(en_sbox),
        .en_pbox(en_pbox),
        .en_feistel(en_feistel),
        .en_key_schedule(en_key_schedule),
        .sel_input(sel_input),
        .sel_output(sel_output),
        .state(state)
    );
    
    // Tạo tín hiệu đồng hồ 10ns (100MHz)
    always #5 clk = ~clk;
    
    // Khai báo task để kiểm tra và hiển thị trạng thái
    task check_state;
        input [1:0] expected_state;
        input string state_name;
        begin
            if (state == expected_state)
                $display("PASS: State is %s as expected", state_name);
            else
                $display("FAIL: State should be %s but is %b", state_name, state);
        end
    endtask
    
    // Khai báo task để kiểm tra các tín hiệu điều khiển
    task check_control_signals;
        input exp_en_ip, exp_en_fp, exp_en_expansion, exp_en_key_mixing;
        input exp_en_sbox, exp_en_pbox, exp_en_feistel, exp_en_key_schedule;
        input exp_sel_input, exp_sel_output;
        begin
            if (en_ip == exp_en_ip && en_fp == exp_en_fp && 
                en_expansion == exp_en_expansion && en_key_mixing == exp_en_key_mixing &&
                en_sbox == exp_en_sbox && en_pbox == exp_en_pbox &&
                en_feistel == exp_en_feistel && en_key_schedule == exp_en_key_schedule &&
                sel_input == exp_sel_input && sel_output == exp_sel_output)
                $display("PASS: Control signals are correct for current state");
            else
                $display("FAIL: Control signals are not as expected");
        end
    endtask
    
    // Khai báo các biến hỗ trợ cho test
    integer i;
    
    // Khối initial chứa các test case
    initial begin
        // Khởi tạo giá trị cho các tín hiệu
        clk = 0;
        rst_n = 0;
        start = 0;
        key_ready = 0;
        data_ready = 0;
        
        // Kích hoạt reset
        #20 rst_n = 1;
        
        // Kiểm tra trạng thái IDLE sau reset
        #10;
        check_state(IDLE, "IDLE");
        
        // Test case 1: Chuyển từ IDLE sang RUN khi start=1 và key/data ready
        $display("\n--- Test Case 1: IDLE to RUN ---");
        key_ready = 1;
        data_ready = 1;
        start = 1;
        #10;
        start = 0; // Bỏ tín hiệu start sau 1 chu kỳ
        check_state(RUN, "RUN");
        check_control_signals(0, 0, 1, 1, 1, 1, 1, 1, 0, 0);
        
        // Test case 2: Theo dõi bộ đếm vòng lặp trong RUN
        $display("\n--- Test Case 2: Round Counter in RUN state ---");
        for (i = 1; i <= 16; i = i + 1) begin
            #10; // Đợi 1 chu kỳ đồng hồ
            $display("Round counter: %0d", round_count);
            if (round_count == i)
                $display("PASS: Round counter is correct");
            else
                $display("FAIL: Round counter should be %0d but is %0d", i, round_count);
                
            // Kiểm tra tín hiệu en_fp trong vòng cuối cùng
            if (i == 16) begin
                if (en_fp == 1)
                    $display("PASS: Final Permutation enabled in last round");
                else
                    $display("FAIL: Final Permutation should be enabled in last round");
            end
        end
        
        // Test case 3: Chuyển từ RUN sang DONE sau 16 vòng
        $display("\n--- Test Case 3: RUN to DONE ---");
        #10; // Đợi thêm 1 chu kỳ sau vòng 16
        check_state(DONE, "DONE");
        if (done == 1 && sel_output == 1)
            $display("PASS: done and sel_output signals are active in DONE state");
        else
            $display("FAIL: done and sel_output signals should be active in DONE state");
            
        // Test case 4: Chuyển từ DONE về IDLE
        $display("\n--- Test Case 4: DONE to IDLE ---");
        #10;
        check_state(IDLE, "IDLE");
        
        // Test case 5: Kiểm tra trạng thái ERROR
        $display("\n--- Test Case 5: ERROR state ---");
        key_ready = 0; // Key chưa sẵn sàng
        data_ready = 1;
        start = 1;
        #10;
        start = 0;
        check_state(ERROR, "ERROR");
        if (error == 1)
            $display("PASS: error signal is active in ERROR state");
        else
            $display("FAIL: error signal should be active in ERROR state");
        
        // Test case 6: Khôi phục từ ERROR
        $display("\n--- Test Case 6: Recovery from ERROR ---");
        key_ready = 1;
        data_ready = 1;
        start = 1;
        #10;
        start = 0;
        check_state(IDLE, "IDLE");
        
        // Kết thúc mô phỏng
        #20;
        $display("\n--- Simulation complete ---");
        $finish;
    end
    
    // Tạo file waveform để xem kết quả
    initial begin
        $dumpfile("des_control_unit_tb.vcd");
        $dumpvars(0, des_control_unit_tb);
    end

endmodule

des/des_control_unit_tb.vcd
$date
	Sun Sep 28 23:20:04 2025
$end
$version
	Icarus Verilog
$end
$timescale
	1ps
$end
$scope module des_control_unit_tb $end
$var wire 2 ! state [1:0] $end
$var wire 1 " sel_output $end
$var wire 1 # sel_input $end
$var wire 5 $ round_count [4:0] $end
$var wire 1 % error $end
$var wire 1 & en_sbox $end
$var wire 1 ' en_pbox $end
$var wire 1 ( en_key_schedule $end
$var wire 1 ) en_key_mixing $end
$var wire 1 * en_ip $end
$var wire 1 + en_fp $end
$var wire 1 , en_feistel $end
$var wire 1 - en_expansion $end
$var wire 1 . done $end
$var parameter 2 / DONE $end
$var parameter 2 0 ERROR $end
$var parameter 2 1 IDLE $end
$var parameter 2 2 RUN $end
$var reg 1 3 clk $end
$var reg 1 4 data_ready $end
$var reg 1 5 key_ready $end
$var reg 1 6 rst_n $end
$var reg 1 7 start $end
$var integer 32 8 i [31:0] $end
$scope module dut $end
$var wire 1 3 clk $end
$var wire 1 4 data_ready $end
$var wire 1 5 key_ready $end
$var wire 1 6 rst_n $end
$var wire 1 7 start $end
$var parameter 2 9 DONE $end
$var parameter 2 : ERROR $end
$var parameter 2 ; IDLE $end
$var parameter 2 < RUN $end
$var reg 1 . done $end
$var reg 1 - en_expansion $end
$var reg 1 , en_feistel $end
$var reg 1 + en_fp $end
$var reg 1 * en_ip $end
$var reg 1 ) en_key_mixing $end
$var reg 1 ( en_key_schedule $end
$var reg 1 ' en_pbox $end
$var reg 1 & en_sbox $end
$var reg 1 % error $end
$var reg 2 = next_state [1:0] $end
$var reg 5 > round_count [4:0] $end
$var reg 1 # sel_input $end
$var reg 1 " sel_output $end
$var reg 2 ? state [1:0] $end
$upscope $end
$scope task check_control_signals $end
$var reg 1 @ exp_en_expansion $end
$var reg 1 A exp_en_feistel $end
$var reg 1 B exp_en_fp $end
$var reg 1 C exp_en_ip $end
$var reg 1 D exp_en_key_mixing $end
$var reg 1 E exp_en_key_schedule $end
$var reg 1 F exp_en_pbox $end
$var reg 1 G exp_en_sbox $end
$var reg 1 H exp_sel_input $end
$var reg 1 I exp_sel_output $end
$upscope $end
$scope task check_state $end
$var reg 2 J expected_state [1:0] $end
$upscope $end
$upscope $end
$enddefinitions $end
$comment Show the parameter values. $end
$dumpall
b1 <
b0 ;
b11 :
b10 9
b1 2
b0 1
b11 0
b10 /
$end
#0
$dumpvars
bx J
xI
xH
xG
xF
xE
xD
xC
xB
xA
x@
b0 ?
b0 >
b0 =
bx 8
07
06
05
04
03
0.
0-
0,
0+
0*
0)
0(
0'
0&
0%
b0 $
1#
0"
b0 !
$end
#5000
13
#10000
03
#15000
13
#20000
03
16
#25000
13
#30000
1(
1*
1#
b1 =
03
17
14
15
b0 J
#35000
1,
1'
1&
1)
1-
0#
1(
0*
b1 !
b1 ?
13
#40000
1(
1,
1'
1&
1)
1-
03
b1 8
0I
0H
1E
1A
1F
1G
1D
1@
0B
0C
b1 J
07
#45000
1(
1,
1'
1&
1)
1-
b1 $
b1 >
13
#50000
03
b10 8
#55000
1(
1,
1'
1&
1)
1-
b10 $
b10 >
13
#60000
03
b11 8
#65000
1(
1,
1'
1&
1)
1-
b11 $
b11 >
13
#70000
03
b100 8
#75000
1(
1,
1'
1&
1)
1-
b100 $
b100 >
13
#80000
03
b101 8
#85000
1(
1,
1'
1&
1)
1-
b101 $
b101 >
13
#90000
03
b110 8
#95000
1(
1,
1'
1&
1)
1-
b110 $
b110 >
13
#100000
03
b111 8
#105000
1(
1,
1'
1&
1)
1-
b111 $
b111 >
13
#110000
03
b1000 8
#115000
1(
1,
1'
1&
1)
1-
b1000 $
b1000 >
13
#120000
03
b1001 8
#125000
1(
1,
1'
1&
1)
1-
b1001 $
b1001 >
13
#130000
03
b1010 8
#135000
1(
1,
1'
1&
1)
1-
b1010 $
b1010 >
13
#140000
03
b1011 8
#145000
1(
1,
1'
1&
1)
1-
b1011 $
b1011 >
13
#150000
03
b1100 8
#155000
1(
1,
1'
1&
1)
1-
b1100 $
b1100 >
13
#160000
03
b1101 8
#165000
1(
1,
1'
1&
1)
1-
b1101 $
b1101 >
13
#170000
03
b1110 8
#175000
1(
1,
1'
1&
1)
1-
b1110 $
b1110 >
13
#180000
03
b1111 8
#185000
1(
1,
1'
1&
1)
1-
b1111 $
b1111 >
13
#190000
03
b10000 8
#195000
1+
1(
1,
1'
1&
1)
1-
b10 =
b10000 $
b10000 >
13
#200000
03
b10001 8
#205000
b0 =
1"
1.
0(
0,
0'
0&
0)
0-
0+
b10 !
b10 ?
13
#210000
03
b10 J
#215000
1#
0"
0.
b0 !
b0 ?
13
#220000
b11 =
1#
03
17
05
b0 J
#225000
1%
0#
b0 $
b0 >
b11 !
b11 ?
13
#230000
b0 =
1%
03
15
b11 J
17
#235000
1(
1*
1#
0%
b1 =
b0 !
b0 ?
13
#240000
b0 =
1#
0(
0*
03
b0 J
07
